collective.saml2-1.5-py2.7-nspkg.pth
collective/saml2/__init__.py
collective/saml2/idpsso.py
collective/saml2/interfaces.py
collective/saml2/testing.py
collective/saml2/tests.py
collective/saml2/bindings/__init__.py
collective/saml2/bindings/_auth.py
collective/saml2/bindings/_sp.py
collective/saml2/bindings/_wsa.py
collective/saml2/bindings/_wsu.py
collective/saml2/bindings/ws_fed.py
collective/saml2/browser/__init__.py
collective.saml2-1.5.dist-info/METADATA
collective.saml2-1.5.dist-info/WHEEL
collective.saml2-1.5.dist-info/entry_points.txt
collective.saml2-1.5.dist-info/namespace_packages.txt
collective.saml2-1.5.dist-info/top_level.txt
collective.saml2-1.5.dist-info/RECORD
